README.md
setup.cfg
setup.py
vicorrect/__init__.py
vicorrect.egg-info/PKG-INFO
vicorrect.egg-info/SOURCES.txt
vicorrect.egg-info/dependency_links.txt
vicorrect.egg-info/requires.txt
vicorrect.egg-info/top_level.txt
vicorrect/datastructures/__init__.py
vicorrect/datastructures/node.py
vicorrect/datastructures/phanso.py
vicorrect/datastructures/prefixtree.py
vicorrect/datastructures/sentence.py
vicorrect/datastructures/specialdict.py
vicorrect/datastructures/trie.py
vicorrect/machine_learning/__init__.py
vicorrect/machine_learning/hmm.py
vicorrect/model/__init__.py
vicorrect/model/add_accents.py