Metadata-Version: 2.1
Name: vicorrect
Version: 0.0.2
Summary: Helpful tool to guess correct vietnamese sentence
Home-page: https://github.com/lvhanh270597/correct_vietnamese_sentence
Author: Hanh.Le Van
Author-email: lvhanh.270597@gmail.com
License: UNKNOWN
Platform: UNKNOWN
Classifier: Programming Language :: Python :: 3
